README.md
setup.cfg
setup.py
simprod/__init__.py
simprod.egg-info/PKG-INFO
simprod.egg-info/SOURCES.txt
simprod.egg-info/dependency_links.txt
simprod.egg-info/requires.txt
simprod.egg-info/top_level.txt
simprod/simjob/__init__.py
simprod/simjob/simjob.py
simprod/simjob/scripts/GetEvtType.py
simprod/simjob/scripts/LSFUtils.py
simprod/simjob/scripts/MoveJobs.py
simprod/simjob/scripts/ScreenUtils.py
simprod/simjob/scripts/SlurmUtils.py
simprod/simjob/scripts/Status.py
simprod/simjob/scripts/__init__.py
simprod/simjob/scripts/submit.py
simprod/simjob/scripts/utils.py
simprod/simjob/setup/__init__.py