Metadata-Version: 1.1
Name: simprod
Version: 1.0
Summary: Mini framework to send LHCb simulation jobs into lxplus or a slurm batch system (with access to cvmfs)!
Home-page: https://github.com/marinang/SimulationProduction
Author: Matthieu Marinangeli
Author-email: matthieu.marinangeli@cern.ch
License: GPL-3.0
Platform: Any
Classifier: Programming Language :: Python :: 2.7
Classifier: Programming Language :: Python :: 3.4
Classifier: Programming Language :: Python :: 3.5
Classifier: Programming Language :: Python :: 3.6
Classifier: Programming Language :: Python :: 3.7
